dsrl/__init__.py
dsrl/infos.py
dsrl/offline_env.py
dsrl/test.py
dsrl/offline_bullet_safety_gym/__init__.py
dsrl/offline_bullet_safety_gym/gym_envs.py
dsrl/offline_metadrive/__init__.py
dsrl/offline_metadrive/gym_envs.py
dsrl/offline_safety_gymnasium/__init__.py
dsrl/offline_safety_gymnasium/gym_envs.py
dsrl-0.1.0.dist-info/LICENSE
dsrl-0.1.0.dist-info/METADATA
dsrl-0.1.0.dist-info/WHEEL
dsrl-0.1.0.dist-info/top_level.txt
dsrl-0.1.0.dist-info/RECORD
