Metadata-Version: 2.1
Name: dsrl
Version: 0.1.0
Summary: Datasets for Offline Safe Reinforcement Learning
Home-page: https://github.com/liuzuxin/dsrl
Author: DSRL contributors
Author-email: zuxin1997@gmail.com
License: Apache
Keywords: datasets for offline safe reinforcement learning
Classifier: Development Status :: 3 - Alpha
Classifier: Intended Audience :: Science/Research
Classifier: Topic :: Scientific/Engineering :: Artificial Intelligence
Classifier: Topic :: Software Development :: Libraries :: Python Modules
Classifier: License :: OSI Approved :: Apache Software License
Classifier: Programming Language :: Python :: 3.8
Classifier: Programming Language :: Python :: 3.9
Classifier: Programming Language :: Python :: 3.10
Requires-Python: >=3.8
License-File: LICENSE
Requires-Dist: gym (>=0.26.0)
Requires-Dist: pybullet (>=3.0.6)
Requires-Dist: bullet-safety-gym (==1.4.0)
Requires-Dist: safety-gymnasium (==0.4.0)
Requires-Dist: numpy
